{
  "active": false,
  "approval_id": "control_path_diagnosis_20260321_runpod_approval1",
  "approved_by": "Codex supervisor",
  "created_at_utc": "2026-03-21T19:57:16Z",
  "hardware_target": "Runpod 1xH100 pod",
  "kind": "remote_runpod",
  "max_paid_runs": 1,
  "notes": "Approved for exactly one 1xH100 control-path diagnosis run using the brief dated 2026-03-21. Verify approval before any remote action; no other run or hardware target is approved.",
  "revocation_notes": "Trial complete. Pod stopped with no training run started.",
  "revoked_at_utc": "2026-03-21T20:08:53Z",
  "revoked_by": "Codex supervisor",
  "run_id": "control_path_diagnosis_20260321_runpod",
  "schema_version": 1
}
